grand_challenge/__init__.py
grand_challenge-0.1.0.dist-info/METADATA
grand_challenge-0.1.0.dist-info/WHEEL
grand_challenge-0.1.0.dist-info/LICENSE
grand_challenge-0.1.0.dist-info/RECORD
