Metadata-Version: 2.1
Name: grand-challenge
Version: 0.1.0
Summary: Next Generation Grand Challenge Python Client
License: Apache-2.0
Author: James Meakin
Author-email: 12661555+jmsmkn@users.noreply.github.com
Requires-Python: >=3.7,<4.0
Classifier: License :: OSI Approved :: Apache Software License
Classifier: Programming Language :: Python :: 3
Classifier: Programming Language :: Python :: 3.7
Classifier: Programming Language :: Python :: 3.8
Classifier: Programming Language :: Python :: 3.9
Classifier: Programming Language :: Python :: 3.10
Classifier: Programming Language :: Python :: 3.11
